weompy/README.md
weompy/__init__.py
weompy/example.py
weompy/libavcodec.58.134.100.dylib
weompy/libavcodec.58.dylib
weompy/libavcodec.dylib
weompy/libavdevice.58.13.100.dylib
weompy/libavdevice.58.dylib
weompy/libavdevice.dylib
weompy/libavformat.58.76.100.dylib
weompy/libavformat.58.dylib
weompy/libavformat.dylib
weompy/libavutil.56.70.100.dylib
weompy/libavutil.56.dylib
weompy/libavutil.dylib
weompy/libswscale.5.9.100.dylib
weompy/libswscale.5.dylib
weompy/libswscale.dylib
weompy/user_documentation.ipynb
weompy/weompy.cpython-311-darwin.so
weompy/weompy.pyi
weompy/QtCore.framework/Versions/A/QtCore
weompy/QtSerialPort.framework/Versions/A/QtSerialPort
weompy-1.8.194.dist-info/METADATA
weompy-1.8.194.dist-info/WHEEL
weompy-1.8.194.dist-info/top_level.txt
weompy-1.8.194.dist-info/RECORD
