Metadata-Version: 2.4
Name: weompy
Version: 1.8.194
Summary: Python library for controlling WEOM IR cameras
Dynamic: description
Dynamic: description-content-type
Dynamic: summary
